{
    "AX(CDD)": {
        "error": 3.457997526831356e-22,
        "error_type": "SEM",
        "filter_outliers_dict": {
            "filter_outliers": true,
            "iterations": 1,
            "std_devs": 2
        },
        "fit": "average",
        "modifier_error": 4.341457641976761e-06,
        "modifier_value": 7.4260584240923045e-06,
        "value": 7.426058424092307e-06
    },
    "H1": {
        "error": 0.0077774093104540035,
        "error_type": "SEM",
        "filter_outliers_dict": {
            "filter_outliers": true,
            "iterations": 1,
            "std_devs": 2
        },
        "fit": "average",
        "modifier_error": 0.0,
        "modifier_value": 0.0,
        "value": -0.0651840763211647
    },
    "H2": {
        "error": 0.012213259043499156,
        "error_type": "SEM",
        "filter_outliers_dict": {
            "filter_outliers": true,
            "iterations": 1,
            "std_devs": 2
        },
        "fit": "average",
        "modifier_error": 0.0,
        "modifier_value": 0.0,
        "value": 0.39565808413714276
    },
    "L1": {
        "error": 0.007041579412296207,
        "error_type": "SEM",
        "filter_outliers_dict": {
            "filter_outliers": true,
            "iterations": 1,
            "std_devs": 2
        },
        "fit": "average",
        "modifier_error": 0.0,
        "modifier_value": 0.0,
        "value": -0.001319218436489062
    },
    "L2(CDD)": {
        "error": 1.378428712098937e-23,
        "error_type": "SEM",
        "filter_outliers_dict": {
            "filter_outliers": true,
            "iterations": 1,
            "std_devs": 10
        },
        "fit": "average",
        "modifier_error": 1.1486417248191402e-06,
        "modifier_value": 5.198240896864614e-07,
        "value": 5.198240896864615e-07
    }
}